louvre/__init__.py
louvre/coingecko/__init__.py
louvre/coingecko/client.py
louvre/coingecko/format.py
louvre-1.0.1.dist-info/METADATA
louvre-1.0.1.dist-info/WHEEL
louvre-1.0.1.dist-info/RECORD
